toc/__init__.py
toc-0.0.14.dist-info/LICENSE
toc-0.0.14.dist-info/WHEEL
toc-0.0.14.dist-info/METADATA
toc-0.0.14.dist-info/RECORD
